bioguider/__init__.py
bioguider/agents/__init__.py
bioguider/agents/agent_task.py
bioguider/agents/agent_tools.py
bioguider/agents/agent_utils.py
bioguider/agents/collection_execute_step.py
bioguider/agents/collection_observe_step.py
bioguider/agents/collection_plan_step.py
bioguider/agents/collection_task.py
bioguider/agents/collection_task_utils.py
bioguider/agents/common_agent.py
bioguider/agents/common_agent_2step.py
bioguider/agents/common_conversation.py
bioguider/agents/common_step.py
bioguider/agents/consistency_collection_step.py
bioguider/agents/consistency_evaluation_task.py
bioguider/agents/consistency_evaluation_task_utils.py
bioguider/agents/consistency_observe_step.py
bioguider/agents/consistency_query_step.py
bioguider/agents/dockergeneration_execute_step.py
bioguider/agents/dockergeneration_observe_step.py
bioguider/agents/dockergeneration_plan_step.py
bioguider/agents/dockergeneration_task.py
bioguider/agents/dockergeneration_task_utils.py
bioguider/agents/evaluation_installation_task.py
bioguider/agents/evaluation_readme_task.py
bioguider/agents/evaluation_submission_requirements_task.py
bioguider/agents/evaluation_task.py
bioguider/agents/evaluation_tutorial_task.py
bioguider/agents/evaluation_tutorial_task_prompts.py
bioguider/agents/evaluation_userguide_prompts.py
bioguider/agents/evaluation_userguide_task.py
bioguider/agents/evaluation_utils.py
bioguider/agents/identification_execute_step.py
bioguider/agents/identification_observe_step.py
bioguider/agents/identification_plan_step.py
bioguider/agents/identification_task.py
bioguider/agents/identification_task_utils.py
bioguider/agents/peo_common_step.py
bioguider/agents/prompt_utils.py
bioguider/agents/python_ast_repl_tool.py
bioguider/agents/rag_collection_task.py
bioguider/conversation.py
bioguider/database/code_structure_db.py
bioguider/database/summarized_file_db.py
bioguider/generation/__init__.py
bioguider/generation/benchmark_metrics.py
bioguider/generation/change_planner.py
bioguider-0.2.52.dist-info/LICENSE
bioguider-0.2.52.dist-info/METADATA
bioguider-0.2.52.dist-info/WHEEL
bioguider-0.2.52.dist-info/RECORD
