Metadata-Version: 2.3
Name: bioguider
Version: 0.2.52
Summary: An AI-Powered package to help biomedical developers to generate clear documentation
License: MIT
Author: Cankun Wang
Author-email: Cankun.Wang@osumc.edu
Requires-Python: >=3.11,<4.0
Classifier: Intended Audience :: Developers
Classifier: Intended Audience :: Science/Research
Classifier: License :: OSI Approved :: MIT License
Classifier: Natural Language :: English
Classifier: Operating System :: OS Independent
Classifier: Programming Language :: Python
Classifier: Programming Language :: Python :: 3
Classifier: Programming Language :: Python :: 3.11
Classifier: Programming Language :: Python :: 3.12
Classifier: Programming Language :: Python :: 3.13
Classifier: Topic :: Scientific/Engineering :: Bio-Informatics
Requires-Dist: adalflow (>=1.0.4,<2.0.0)
Requires-Dist: azure-ai-formrecognizer (>=3.3.3,<4.0.0)
Requires-Dist: azure-ai-textanalytics (>=5.3.0,<6.0.0)
Requires-Dist: azure-core (>=1.36.0,<2.0.0)
Requires-Dist: azure-identity (>=1.25.1,<2.0.0)
Requires-Dist: beautifulsoup4 (>=4.13.3,<5.0.0)
Requires-Dist: binaryornot (>=0.4.4,<0.5.0)
Requires-Dist: faiss-cpu (>=1.11.0,<2.0.0)
Requires-Dist: grandalf (>=0.8,<0.9)
Requires-Dist: langchain (>=0.3.20,<0.4.0)
Requires-Dist: langchain-anthropic (>=0.3.10,<0.4.0)
Requires-Dist: langchain-deepseek (>=0.1.2,<0.2.0)
Requires-Dist: langchain-experimental (>=0.3.4,<0.4.0)
Requires-Dist: langchain-google-genai (>=2.1.4,<3.0.0)
Requires-Dist: langchain-openai (>=0.3.8,<0.4.0)
Requires-Dist: langgraph (>=0.3.11,<0.4.0)
Requires-Dist: markdownify (>=1.1.0,<2.0.0)
Requires-Dist: nanoid (>=2.0.0,<3.0.0)
Requires-Dist: pydantic (>=2.10.6,<3.0.0)
Requires-Dist: pydantic-settings (>=2.8.1,<3.0.0)
Requires-Dist: pyphen (>=0.17.2,<0.18.0)
Requires-Dist: pytest (>=8.3.5,<9.0.0)
Requires-Dist: python-dotenv (>=1.0.1,<2.0.0)
Requires-Dist: python-iso639 (>=2025.2.18,<2026.0.0)
Requires-Dist: python-magic (>=0.4.27,<0.5.0)
Requires-Dist: tenacity (>=9.1.2,<10.0.0)
Requires-Dist: textstat (>=0.7.6,<0.8.0)
Requires-Dist: tiktoken (>=0.9.0,<0.10.0)
Requires-Dist: tqdm (>=4.67.1,<5.0.0)
